slamop/__init__.py
slamop-0.0.13.dist-info/METADATA
slamop-0.0.13.dist-info/WHEEL
slamop-0.0.13.dist-info/top_level.txt
slamop-0.0.13.dist-info/RECORD
